clingexplaid/__init__.py
clingexplaid/py.typed
clingexplaid/cli/style/mus.py
clingexplaid/exceptions/__init__.py
clingexplaid/mus/__init__.py
clingexplaid/mus/core_computer.py
clingexplaid/preprocessors/__init__.py
clingexplaid/preprocessors/preprocessor_assumption.py
clingexplaid/propagators/__init__.py
clingexplaid/propagators/constants.py
clingexplaid/propagators/propagator_solver_decisions.py
clingexplaid/transformers/__init__.py
clingexplaid/transformers/constants.py
clingexplaid/transformers/transformer_constraint.py
clingexplaid/transformers/transformer_fact.py
clingexplaid/transformers/transformer_optimization_remover.py
clingexplaid/transformers/transformer_rule_id.py
clingexplaid/transformers/transformer_rule_splitter.py
clingexplaid/unsat_constraints/__init__.py
clingexplaid/unsat_constraints/constants.py
clingexplaid/unsat_constraints/unsat_constraint_computer.py
clingexplaid/utils/__init__.py
clingexplaid/utils/logging.py
clingexplaid/utils/match.py
clingexplaid/utils/parser.py
clingexplaid/utils/symbols.py
clingexplaid/utils/types.py
clingexplaid-1.3.5.dist-info/licenses/LICENSE
clingexplaid-1.3.5.dist-info/METADATA
clingexplaid-1.3.5.dist-info/WHEEL
clingexplaid-1.3.5.dist-info/top_level.txt
clingexplaid-1.3.5.dist-info/RECORD
