Metadata-Version: 2.4
Name: clingexplaid
Version: 1.3.5
Summary: Tools to aid the development of explanation systems using clingo
Author-email: Hannes Weichelt <hweichelt@uni-potsdam.de>, Susana Hahn <susuhahnml@yahoo.com.mx>
Maintainer-email: Hannes Weichelt <hweichelt@uni-potsdam.de>
License: MIT License
Project-URL: Homepage, https://github.com/potassco/clingo-explaid
Project-URL: Source, https://github.com/potassco/clingo-explaid
Project-URL: Issues, https://github.com/potassco/clingo-explaid/issues
Classifier: Development Status :: 4 - Beta
Classifier: Environment :: Console
Classifier: Intended Audience :: Developers
Classifier: License :: OSI Approved :: MIT License
Classifier: Programming Language :: Python :: 3
Classifier: Programming Language :: Python :: 3 :: Only
Classifier: Programming Language :: Python :: 3.10
Classifier: Programming Language :: Python :: 3.11
Classifier: Programming Language :: Python :: 3.12
Classifier: Operating System :: OS Independent
Classifier: Topic :: Software Development :: Libraries :: Python Modules
Classifier: Typing :: Typed
Requires-Python: >=3.10
License-File: LICENSE
Requires-Dist: clingo>=5.7.1
Requires-Dist: autoflake
Provides-Extra: format
Requires-Dist: black; extra == "format"
Requires-Dist: isort; extra == "format"
Requires-Dist: autoflake; extra == "format"
Provides-Extra: lint-pylint
Requires-Dist: pylint; extra == "lint-pylint"
Provides-Extra: typecheck
Requires-Dist: types-setuptools; extra == "typecheck"
Requires-Dist: mypy; extra == "typecheck"
Provides-Extra: test
Requires-Dist: coverage[toml]; extra == "test"
Provides-Extra: doc
Requires-Dist: sphinx; extra == "doc"
Requires-Dist: furo; extra == "doc"
Requires-Dist: nbsphinx; extra == "doc"
Requires-Dist: sphinx_copybutton; extra == "doc"
Requires-Dist: myst-parser; extra == "doc"
Provides-Extra: dev
Requires-Dist: clingexplaid[lint_pylint,test,typecheck]; extra == "dev"
Dynamic: license-file
